MANIFEST.in
README
setup.cfg
setup.py
doc/Install.txt
doc/LICENSE
doc/VERSION
doc/hash.txt
doc/security.txt
doc/sym_crypto.txt
lib/cryha/__init__.py
lib/cryha/common.py
lib/cryha/crypter.py
lib/cryha/hasher.py
lib/cryha.egg-info/PKG-INFO
lib/cryha.egg-info/SOURCES.txt
lib/cryha.egg-info/dependency_links.txt
lib/cryha.egg-info/not-zip-safe
lib/cryha.egg-info/requires.txt
lib/cryha.egg-info/top_level.txt
test/.coverage
test/test_argument.py
test/test_argument.pyc
test/test_cryha.py
test/test_cryha.pyc