Metadata-Version: 1.0
Name: cryha
Version: 1.0
Summary: Toolkit for securing information into a database
Home-page: http://bitbucket.org/ares/cryha/
Author: Jonas Melian
Author-email: devel@jonasmelian.com
License: Apache License, Version 2.0
Keywords: security cryptography crypto symmetric hash database
Platform: any
Classifier: Development Status :: 5 - Production/Stable
Classifier: Environment :: Web Environment
Classifier: Environment :: Other Environment
Classifier: Intended Audience :: Developers
Classifier: License :: OSI Approved :: Apache Software License
Classifier: Operating System :: OS Independent
Classifier: Programming Language :: Python
Classifier: Topic :: Database
Classifier: Topic :: Security :: Cryptography
